checkits-2.0.1.dist-info/METADATA
checkits-2.0.1.dist-info/RECORD
checkits-2.0.1.dist-info/WHEEL
checkits-2.0.1.dist-info/entry_points.txt
checkits-2.0.1.dist-info/top_level.txt
main/__init__.py
main/__main__.py
main/main.py
