Metadata-Version: 2.1
Name: checkits
Version: 2.0.1
Summary: UNKNOWN
Home-page: https://github.com/oss-a-1/sqlitedb
Author: hy univ. oss team a-1
Author-email: suspicions@naver.com
License: mit license
Download-URL: https://github.com/oss-a-1/sqlitedb
Platform: UNKNOWN
Requires-Dist: colorama
